xnxx_api/__init__.py
xnxx_api/xnxx_api.py
xnxx_api/modules/__init__.py
xnxx_api/modules/category.py
xnxx_api/modules/consts.py
xnxx_api/modules/errors.py
xnxx_api/modules/search_filters.py
xnxx_api/tests/__init__.py
xnxx_api/tests/conftest.py
xnxx_api/tests/test_search.py
xnxx_api/tests/test_user.py
xnxx_api/tests/test_video.py
xnxx_api_async-1.5.3.dist-info/LICENSE
xnxx_api_async-1.5.3.dist-info/METADATA
xnxx_api_async-1.5.3.dist-info/WHEEL
xnxx_api_async-1.5.3.dist-info/entry_points.txt
xnxx_api_async-1.5.3.dist-info/top_level.txt
xnxx_api_async-1.5.3.dist-info/RECORD
