Metadata-Version: 2.2
Name: xnxx_api-async
Version: 1.5.3
Summary: A Python API for the Porn Site xnxx.com
Home-page: https://github.com/EchterAlsFake/xnxx_api
Author: Johannes Habel
Author-email: EchterAlsFake@proton.me
License: LGPLv3
Classifier: License :: OSI Approved :: GNU Lesser General Public License v3 (LGPLv3)
Classifier: Programming Language :: Python
License-File: LICENSE
Requires-Dist: bs4
Requires-Dist: eaf_base_api-async
Dynamic: author
Dynamic: author-email
Dynamic: classifier
Dynamic: description
Dynamic: description-content-type
Dynamic: home-page
Dynamic: license
Dynamic: requires-dist
Dynamic: summary
